brick/__init__.py
brick/azr.py
brick/configuration.py
brick/constants.py
brick/data.py
brick/level.py
brick/nodata.py
brick/output.py
brick/parameter.py
brick/utility.py
brick_james-0.2.3.dist-info/LICENSE
brick_james-0.2.3.dist-info/METADATA
brick_james-0.2.3.dist-info/WHEEL
brick_james-0.2.3.dist-info/top_level.txt
brick_james-0.2.3.dist-info/RECORD
