Metadata-Version: 2.1
Name: brick-james
Version: 0.2.3
Summary: A Python interface to AZURE2 that makes it easy to sample R-matrix parameters.
Home-page: https://github.com/odell/brick
Author: Daniel Odell
Author-email: dodell@ohio.edu
Project-URL: Bug Tracker, https://github.com/odell/brick/issues
Classifier: Programming Language :: Python :: 3
Classifier: License :: OSI Approved :: MIT License
Classifier: Operating System :: POSIX :: Linux
Classifier: Operating System :: Unix
Requires-Python: >=3.6
License-File: LICENSE
